localaws/__init__.py
localaws/cli.py
localaws/utils.py
localaws-0.1.1.dist-info/LICENSE
localaws-0.1.1.dist-info/METADATA
localaws-0.1.1.dist-info/WHEEL
localaws-0.1.1.dist-info/entry_points.txt
localaws-0.1.1.dist-info/top_level.txt
localaws-0.1.1.dist-info/RECORD
