Metadata-Version: 2.1
Name: localaws
Version: 0.1.1
Summary: Run local Python scripts with AWS profiles - perfect for local testing with different AWS environments
Home-page: https://github.com/yourusername/localaws
Author-email: Sourav Padhi <ssupsourav@gmail.com>
License: MIT License
Requires-Python: >=3.7
License-File: LICENSE
Requires-Dist: click>=8.0.0
Requires-Dist: boto3>=1.26.0
